xyz_appoint/__init__.py
xyz_appoint/admin.py
xyz_appoint/apis.py
xyz_appoint/apps.py
xyz_appoint/authentications.py
xyz_appoint/helper.py
xyz_appoint/mixins.py
xyz_appoint/models.py
xyz_appoint/permissions.py
xyz_appoint/serializers.py
xyz_appoint/migrations/0001_initial.py
xyz_appoint/migrations/__init__.py
xyz_appoint-0.0.4.dist-info/METADATA
xyz_appoint-0.0.4.dist-info/WHEEL
xyz_appoint-0.0.4.dist-info/top_level.txt
xyz_appoint-0.0.4.dist-info/RECORD
